.coveragerc
.gitignore
LICENSE.txt
MANIFEST.in
README.rst
README.txt
pyproject.toml
pytest.ini
repr_html.ipynb
requirements-database.txt
requirements-docs.txt
requirements-formats.txt
requirements-linting.txt
requirements-optional.txt
requirements-remote.txt
requirements-tests.txt
setup.py
tox.ini
./petl/__init__.py
./petl/comparison.py
./petl/compat.py
./petl/config.py
./petl/errors.py
./petl/version.py
./petl/io/__init__.py
./petl/io/avro.py
./petl/io/base.py
./petl/io/bcolz.py
./petl/io/csv.py
./petl/io/csv_py2.py
./petl/io/csv_py3.py
./petl/io/db.py
./petl/io/db_create.py
./petl/io/db_utils.py
./petl/io/gsheet.py
./petl/io/html.py
./petl/io/json.py
./petl/io/numpy.py
./petl/io/pandas.py
./petl/io/pickle.py
./petl/io/pytables.py
./petl/io/remotes.py
./petl/io/sources.py
./petl/io/text.py
./petl/io/whoosh.py
./petl/io/xls.py
./petl/io/xlsx.py
./petl/io/xlutils_view.py
./petl/io/xml.py
./petl/test/__init__.py
./petl/test/conftest.py
./petl/test/failonerror.py
./petl/test/helpers.py
./petl/test/test_comparison.py
./petl/test/test_fluent.py
./petl/test/test_helpers.py
./petl/test/test_interactive.py
./petl/test/io/__init__.py
./petl/test/io/test_avro.py
./petl/test/io/test_avro_schemas.py
./petl/test/io/test_bcolz.py
./petl/test/io/test_csv.py
./petl/test/io/test_csv_unicode.py
./petl/test/io/test_db.py
./petl/test/io/test_db_create.py
./petl/test/io/test_db_server.py
./petl/test/io/test_gsheet.py
./petl/test/io/test_html.py
./petl/test/io/test_html_unicode.py
./petl/test/io/test_json.py
./petl/test/io/test_json_unicode.py
./petl/test/io/test_jsonl.py
./petl/test/io/test_numpy.py
./petl/test/io/test_pandas.py
./petl/test/io/test_pickle.py
./petl/test/io/test_pytables.py
./petl/test/io/test_remotes.py
./petl/test/io/test_sources.py
./petl/test/io/test_sqlite3.py
./petl/test/io/test_tees.py
./petl/test/io/test_text.py
./petl/test/io/test_text_unicode.py
./petl/test/io/test_whoosh.py
./petl/test/io/test_xls.py
./petl/test/io/test_xlsx.py
./petl/test/io/test_xml.py
petl.egg-info/PKG-INFO
petl.egg-info/SOURCES.txt
petl.egg-info/dependency_links.txt
petl.egg-info/requires.txt
petl.egg-info/top_level.txt
